{
    "key": "group_6213bea70a045",
    "title": "Megamenu",
    "fields": [
        {
            "key": "field_6213beaedebc5",
            "label": "Featured",
            "name": "featured",
            "type": "post_object",
            "instructions": "",
            "required": 0,
            "conditional_logic": 0,
            "wrapper": {
                "width": "",
                "class": "",
                "id": ""
            },
            "post_type": [
                "post",
                "page",
                "work"
            ],
            "taxonomy": "",
            "allow_null": 0,
            "multiple": 1,
            "return_format": "object",
            "ui": 1
        }
    ],
    "location": [
        [
            {
                "param": "nav_menu_item",
                "operator": "==",
                "value": "location\/menu-1"
            }
        ]
    ],
    "menu_order": 0,
    "position": "normal",
    "style": "default",
    "label_placement": "top",
    "instruction_placement": "label",
    "hide_on_screen": "",
    "active": true,
    "description": "",
    "show_in_rest": 0,
    "modified": 1645528705
}